{"file":"sieu_nhe_tex.png","res":{"nhe_7":{"x":1,"y":1,"w":140,"h":94},"nhe_19":{"x":143,"y":1,"w":140,"h":94},"nhe_5":{"x":285,"y":1,"w":140,"h":94},"nhe_9":{"x":1,"y":97,"w":140,"h":94},"nhe_0":{"x":143,"y":97,"w":140,"h":94},"nhe_13":{"x":285,"y":97,"w":140,"h":94},"nhe_6":{"x":1,"y":193,"w":140,"h":94},"nhe_21":{"x":143,"y":193,"w":140,"h":94},"nhe_14":{"x":285,"y":193,"w":140,"h":94},"nhe_8":{"x":1,"y":289,"w":140,"h":94},"nhe_2":{"x":143,"y":289,"w":140,"h":94},"nhe_10":{"x":285,"y":289,"w":140,"h":94},"nhe_15":{"x":1,"y":385,"w":140,"h":94},"nhe_11":{"x":143,"y":385,"w":140,"h":94},"nhe_18":{"x":285,"y":385,"w":140,"h":94},"nhe_4":{"x":1,"y":481,"w":140,"h":94},"nhe_20":{"x":143,"y":481,"w":140,"h":94},"nhe_16":{"x":285,"y":481,"w":140,"h":94},"nhe_22":{"x":1,"y":577,"w":140,"h":94},"nhe_23":{"x":143,"y":577,"w":140,"h":94},"nhe_3":{"x":285,"y":577,"w":140,"h":94},"nhe_1":{"x":1,"y":673,"w":140,"h":94},"nhe_12":{"x":143,"y":673,"w":140,"h":94},"nhe_17":{"x":285,"y":673,"w":140,"h":94}},"mc":{"vuvuzela":{"labels":[{"end":24,"frame":1,"name":"nhe"}],"frameRate":24,"frames":[{"y":-47,"res":"nhe_0","duration":1,"x":-70},{"y":-47,"res":"nhe_1","duration":1,"x":-70},{"y":-47,"res":"nhe_2","duration":1,"x":-70},{"y":-47,"res":"nhe_3","duration":1,"x":-70},{"y":-47,"res":"nhe_4","duration":1,"x":-70},{"y":-47,"res":"nhe_5","duration":1,"x":-70},{"y":-47,"res":"nhe_6","duration":1,"x":-70},{"y":-47,"res":"nhe_7","duration":1,"x":-70},{"y":-47,"res":"nhe_8","duration":1,"x":-70},{"y":-47,"res":"nhe_9","duration":1,"x":-70},{"y":-47,"res":"nhe_10","duration":1,"x":-70},{"y":-47,"res":"nhe_11","duration":1,"x":-70},{"y":-47,"res":"nhe_12","duration":1,"x":-70},{"y":-47,"res":"nhe_13","duration":1,"x":-70},{"y":-47,"res":"nhe_14","duration":1,"x":-70},{"y":-47,"res":"nhe_15","duration":1,"x":-70},{"y":-47,"res":"nhe_16","duration":1,"x":-70},{"y":-47,"res":"nhe_17","duration":1,"x":-70},{"y":-47,"res":"nhe_18","duration":1,"x":-70},{"y":-47,"res":"nhe_19","duration":1,"x":-70},{"y":-47,"res":"nhe_20","duration":1,"x":-70},{"y":-47,"res":"nhe_21","duration":1,"x":-70},{"y":-47,"res":"nhe_22","duration":1,"x":-70},{"y":-47,"res":"nhe_23","duration":1,"x":-70}],"events":[]}}}